zkp_rust_client-0.1.0.dist-info/METADATA
zkp_rust_client-0.1.0.dist-info/WHEEL
zkp_rust_client/__init__.py
zkp_rust_client/zkp_rust_client.cpython-312-x86_64-linux-gnu.so
zkp_rust_client-0.1.0.dist-info/RECORD
