Metadata-Version: 2.4
Name: zkp-rust-client
Version: 0.1.0
Classifier: Development Status :: 4 - Beta
Classifier: Intended Audience :: Developers
Classifier: License :: OSI Approved :: MIT License
Classifier: Operating System :: OS Independent
Classifier: Programming Language :: Python :: 3
Classifier: Programming Language :: Python :: 3.7
Classifier: Programming Language :: Python :: 3.8
Classifier: Programming Language :: Python :: 3.9
Classifier: Programming Language :: Python :: 3.10
Classifier: Programming Language :: Python :: 3.11
Classifier: Programming Language :: Python :: 3.12
Classifier: Topic :: Security :: Cryptography
Classifier: Topic :: Software Development :: Libraries :: Python Modules
Classifier: Topic :: Scientific/Engineering :: Mathematics
Requires-Dist: pytest>=6.0 ; extra == 'dev'
Requires-Dist: pytest-cov>=2.0 ; extra == 'dev'
Requires-Dist: black>=21.0 ; extra == 'dev'
Requires-Dist: isort>=5.0 ; extra == 'dev'
Requires-Dist: mypy>=0.800 ; extra == 'dev'
Provides-Extra: dev
Summary: A Rust implementation of Zero-Knowledge Proofs (ZKP) using the Groth16 proving system
Keywords: zkp,zero-knowledge-proofs,groth16,cryptography,blockchain
Author-email: Your Name <your.email@example.com>
Maintainer-email: Your Name <your.email@example.com>
License: MIT
Requires-Python: >=3.7
Project-URL: Homepage, https://github.com/Metaway-Holdings/ark-zkp
Project-URL: Repository, https://github.com/Metaway-Holdings/ark-zkp
Project-URL: Documentation, https://github.com/Metaway-Holdings/ark-zkp#readme
Project-URL: Bug Tracker, https://github.com/Metaway-Holdings/ark-zkp/issues
